MANIFEST.in
README.rst
setup.py
grapheekdb/__init__.py
grapheekdb.egg-info/PKG-INFO
grapheekdb.egg-info/SOURCES.txt
grapheekdb.egg-info/dependency_links.txt
grapheekdb.egg-info/entry_points.txt
grapheekdb.egg-info/not-zip-safe
grapheekdb.egg-info/requires.txt
grapheekdb.egg-info/top_level.txt
grapheekdb/algorithms/__init__.py
grapheekdb/algorithms/paths/__init__.py
grapheekdb/algorithms/paths/astar.py
grapheekdb/algorithms/paths/dijkstra.py
grapheekdb/backends/__init__.py
grapheekdb/backends/data/__init__.py
grapheekdb/backends/data/base.py
grapheekdb/backends/data/filtertools.py
grapheekdb/backends/data/indexes.py
grapheekdb/backends/data/keys.py
grapheekdb/backends/data/kyotocab.py
grapheekdb/backends/data/localmem.py
grapheekdb/backends/data/lookups.py
grapheekdb/backends/data/operations.py
grapheekdb/backends/data/optimizer.py
grapheekdb/backends/data/ordertools.py
grapheekdb/backends/data/shelvefile.py
grapheekdb/backends/data/sqlite.py
grapheekdb/backends/data/symaslmdb.py
grapheekdb/client/__init__.py
grapheekdb/client/api.py
grapheekdb/lib/__init__.py
grapheekdb/lib/exceptions.py
grapheekdb/lib/expressions.py
grapheekdb/lib/nx.py
grapheekdb/lib/readwrite.py
grapheekdb/lib/undef.py
grapheekdb/lib/validations.py
grapheekdb/server/__init__.py
grapheekdb/server/dummy_scripts.py
grapheekdb/server/scripts.py
grapheekdb/server/serve.py