Metadata-Version: 1.1
Name: grapheekdb
Version: 0.0.24
Summary: GrapheekDB is a pure Python graph database which is fast and lightweight
Home-page: https://bitbucket.org/nidusfr/grapheekdb
Author: Raphaël Braud
Author-email: grapheekdb@gmail.com
License: GPL v3
Platform: UNKNOWN
Classifier: Development Status :: 3 - Alpha
Classifier: Intended Audience :: Developers
Classifier: License :: OSI Approved :: GNU General Public License v3 (GPLv3)
Classifier: Operating System :: OS Independent
Classifier: Programming Language :: Python :: 2.7
Classifier: Programming Language :: Python :: 3.3
Classifier: Programming Language :: Python :: 3.4
Classifier: Topic :: Database
Classifier: Topic :: Database :: Database Engines/Servers
